README.md
setup.py
monsgrams/__init__.py
monsgrams/api.py
monsgrams/base.py
monsgrams/bot.py
monsgrams/message.py
monsgrams.egg-info/PKG-INFO
monsgrams.egg-info/SOURCES.txt
monsgrams.egg-info/dependency_links.txt
monsgrams.egg-info/requires.txt
monsgrams.egg-info/top_level.txt