Metadata-Version: 2.1
Name: monsgrams
Version: 1.2
Summary: A simple Python library for creating telegram bot.
Home-page: https://github.com/tech-voyager/monsgrams/
Author: grubx64
License: MIT
Requires-Dist: aiohttp>=3.9.3
